fclist.py
fclist_cffi-1.1.2.dist-info/LICENSE
fclist_cffi-1.1.2.dist-info/METADATA
fclist_cffi-1.1.2.dist-info/WHEEL
fclist_cffi-1.1.2.dist-info/top_level.txt
fclist_cffi-1.1.2.dist-info/RECORD
