Metadata-Version: 2.1
Name: fclist-cffi
Version: 1.1.2
Summary: Python cffi bridge to fontconfig's FcFontList/FcFontMatch
Home-page: https://github.com/MonsieurV/python-fclist
Author: Yoan Tournade
Author-email: y@yoantournade.com
License: MIT
Download-URL: https://github.com/MonsieurV/python-fclist/archive/1.1.2.tar.gz
Platform: UNKNOWN
Requires-Dist: cffi
